drfauthshield/__init__.py
drfauthshield/py.typed
drfauthshield-0.0.1.dist-info/METADATA
drfauthshield-0.0.1.dist-info/WHEEL
drfauthshield-0.0.1.dist-info/entry_points.txt
drfauthshield-0.0.1.dist-info/licenses/LICENSE
drfauthshield-0.0.1.dist-info/RECORD
