Metadata-Version: 2.4
Name: drfauthshield
Version: 0.0.1
Summary: A Django REST Framework package offering robust JWT authentication with secure, flexible endpoints.
Project-URL: Homepage, https://github.com/shaileshpandit141/drfauthshield
Project-URL: Documentation, https://shaileshpandit141.github.io/drfauthshield
Project-URL: Source, https://github.com/shaileshpandit141/drfauthshield
Project-URL: Issues, https://github.com/shaileshpandit141/drfauthshield/issues
Project-URL: License, https://github.com/shaileshpandit141/drfauthshield/blob/main/LICENSE
Author-email: Shailesh Pandit <shaileshpandit141@gmail.com>
License: # MIT License
License-File: LICENSE
Keywords: api-auth,auth,authentication,authorization,django,django-rest-framework,drf,drfauthshield,json-web-token,jwt,rest-api,security,token,token-authentication
Classifier: Development Status :: 1 - Planning
Classifier: Framework :: Django
Classifier: Framework :: Django :: 5.0
Classifier: Intended Audience :: Developers
Classifier: License :: OSI Approved :: MIT License
Classifier: Programming Language :: Python :: 3.10
Classifier: Programming Language :: Python :: 3.11
Classifier: Programming Language :: Python :: 3.12
Classifier: Topic :: Internet :: WWW/HTTP
Classifier: Topic :: Security
Classifier: Topic :: Software Development :: Libraries :: Python Modules
Requires-Python: >=3.13
Provides-Extra: dev
Requires-Dist: mypy; extra == 'dev'
Requires-Dist: pytest; extra == 'dev'
Requires-Dist: ruff; extra == 'dev'
